meypycache/__init__.py
meypycache/caches/__init__.py
meypycache/caches/fscache.py
meypycache/core/__init__.py
meypycache/core/files.py
meypycache/core/paramconverter.py
meypycache/core/uuid.py
meypycache-0.2.0.dist-info/LICENSE
meypycache-0.2.0.dist-info/WHEEL
meypycache-0.2.0.dist-info/METADATA
meypycache-0.2.0.dist-info/RECORD
