Metadata-Version: 2.1
Name: meypycache
Version: 0.2.0
Summary: 
Author: Your Name
Author-email: you@example.com
Requires-Python: >=3.8,<4.0
Classifier: Programming Language :: Python :: 3
Classifier: Programming Language :: Python :: 3.10
Classifier: Programming Language :: Python :: 3.8
Classifier: Programming Language :: Python :: 3.9
Requires-Dist: PyYAML (>=6.0,<7.0)
Requires-Dist: loguru (>=0.6.0,<0.7.0)
Requires-Dist: pytest (>=7.0.1,<8.0.0)
Requires-Dist: pytest-lazy-fixture (>=0.6.3,<0.7.0)
